[
    {
        "title": "Huyamba",
        "source": "5Q6OxD3zRfYk5ReQ4e6GSS",
        "artist": "Leningrad",
        "release_year": 2003,
        "country": "USSR"
    },
    {
        "title": "Night Boat To Cairo",
        "source": "1m1PWQeZcDBmFsLCJ5qSdn",
        "artist": "Madness",
        "release_year": 1979,
        "country": "UK"
    },
    {
        "title": "Leave The Door Open",
        "source": "5Q6OxD3zRfYk5ReQ4e6GSS",
        "artist": "Silk Sonic",
        "release_year": 2021,
        "country": "USA"
    },
    {
        "title": "JOS TE VOLIM",
        "source": "66CHdmld3iy8t6ZeNF1LVd",
        "artist": "Novi Fosili",
        "release_year": 1985,
        "country": "Yugoslavia"
    },
    {
        "title": "Wind of Change",
        "source": "3ovjw5HZZv43SxTwApooCM",
        "artist": "Scorpions",
        "release_year": 1990,
        "country": "FR Germany"
    },
    {
        "title": "Nel Blu Dipinto Di Blu",
        "source": "5zyrEv4F3FaLECI8TOKpFM",
        "artist": "Domenico Modugno",
        "release_year": 1958,
        "country": "Italy"
    },
    {
        "title": "Avant Toi",
        "source": "4iNPp0BZ4lBu7bipdWLcWk",
        "artist": "Vitaa & Slimane",
        "release_year": 2019,
        "country": "France"
    },
    {
        "title": "You're Still The One",
        "source": "1wb4P4F0sxAQ2KXrRvsx6n",
        "artist": "Shania Twain",
        "release_year": 1997,
        "country": "Canada"
    },
    {
        "title": "Making Love Out of Nothing At All",
        "source": "01MXkFA8sL7at6txavDErt",
        "artist": "Air Supply",
        "release_year": 1983,
        "country": "Australia"
    },
    {
        "title": "Bamboleo",
        "source": "3iB8eciGU9vZkaDYkz7Ir9",
        "artist": "Gypsy Kings",
        "release_year": 1987,
        "country": "Spain"
    },
    {
        "title": "Uma Casa Portuguesa",
        "source": "3SUs9nP8bxnwyg0NjsueVd",
        "artist": "Amália Rodrigues",
        "release_year": 1953,
        "country": "Portugal"
    },
    {
        "title": "El Cuarto de Tula",
        "source": "7dRfobhDNnsEgB2ZArxA1f",
        "artist": "Buena Vista Social Club",
        "release_year": 1997,
        "country": "Cuba"
    },
    {
        "title": "Belle Helene",
        "source": "3hr5ingOrSNRPAKE0uK3rE",
        "artist": "Doe Maar",
        "release_year": 1982,
        "country": "Netherlands"
    },
    {
        "title": "Aşkım Baksana Bana",
        "source": "6iLnx3xMt6yRQJMiXtyi78",
        "artist": "Nazan Öncel",
        "release_year": 2006,
        "country": "Turkey"
    },
    {
        "title": "Shosholoza",
        "source": "3oZZdkxpgi2lupOSdGJzLS",
        "artist": "Soweto Gospel Choir",
        "release_year": 2020,
        "country": "South Africa"
    },
    {
        "title": "Into the I-LAND",
        "source": "4YvtgtEH5E1pahZu9uzKRy",
        "artist": "IU",
        "release_year": 2020,
        "country": "South Korea"
    },
    {
        "title": "You Belong To Him",
        "source": "74UH2neux1IsLGhW0IOG4j",
        "artist": "1986 Omega Tribe",
        "release_year": 1986,
        "country": "Japan"
    },
    {
        "title": "Selamat Jalan",
        "source": "06CZctheMwPh3Q9hO2S89a",
        "artist": "Tipe-X",
        "release_year": 2001,
        "country": "Indonesia"
    },
    {
        "title": "El Hilwa Di",
        "source": "76ABOCf1e7742zqh0w3vhl",
        "artist": "Dania",
        "release_year": 2006,
        "country": "Egypt"
    },
    {
        "title": "Khallik Behalak",
        "source": "5Q6OxD3zRfYk5ReQ4e6GSS",
        "artist": "Carole Samaha",
        "release_year": 2009,
        "country": "Lebanon"
    },
    {
        "title": "Skelewu",
        "source": "0C63WNrSJOlu62O6lrxRMU",
        "artist": "Davido",
        "release_year": 2013,
        "country": "Nigeria"
    },
    {
        "title": "Jai Ho! (You Are My Destiny)",
        "source": "7Kpqjspw4Y7HrvItIRcBiW",
        "artist": "The Pussycat Dolls & A.R. Rahman",
        "release_year": 2009,
        "country": "India"
    },
    {
        "title": "Cambio Dolor",
        "source": "4kreL49xOapJRVTKl2OcmQ",
        "artist": "Natalia Oreiro",
        "release_year": 1998,
        "country": "Uruguay"
    },
    {
        "title": "If I Let You Go",
        "source": "3St0RlsL0Z0klK1mqWakQm",
        "artist": "Westlife",
        "release_year": 1999,
        "country": "Ireland"
    },
    {
        "title": "Sway",
        "source": "3JtRSUOj7wSAXFG76T89v8",
        "artist": "Bic Runga",
        "release_year": 1997,
        "country": "New Zealand"
    },
    {
        "title": "Take On Me",
        "source": "2WfaOiMkCvy7F5fcp2zZ8L",
        "artist": "a-ha",
        "release_year": 1984,
        "country": "Norway"
    },
    {
        "title": "Money, Money, Money",
        "source": "3lKN03PDeBnXZS7sDukRBt",
        "artist": "ABBA",
        "release_year": 1976,
        "country": "Sweden"
    },
    {
        "title": "Takes 2 To Tango",
        "source": "5zxDXyjuvm6EHOvypeZFEP",
        "artist": "Jari Sillanpää",
        "release_year": 2004,
        "country": "Finland"
    },
    {
        "title": "Any Less",
        "source": "6tedNd3Ni9mA0vpqZpnTDl",
        "artist": "Emmelie de Forest",
        "release_year": 2018,
        "country": "Denmark"
    },
    {
        "title": "Corazon Espinado",
        "source": "2WoqgtWEBbbBKMDN6Becs7",
        "artist": "Santana",
        "release_year": 1999,
        "country": "Mexico"
    },
    {
        "title": "Me Gusta",
        "source": "7e1VoRlNumuEkXlITMHKLE",
        "artist": "Anitta",
        "release_year": 2020,
        "country": "Brazil"
    },
    {
        "title": "Rakevet Layla LeKahir",
        "source": "7BmJu70l6sifbmnlMe3Xzk",
        "artist": "Mashina",
        "release_year": 1985,
        "country": "Israel"
    },
    {
        "title": "Bahama Mama",
        "source": "22VzZnyTH9lH0aXfchLjgm",
        "artist": "Boney M.",
        "release_year": 1979,
        "country": "Jamaica"
    },
    {
        "title": "Chytila jsem motylka",
        "source": "5BRvpMwYYMH4DgwLayHK64",
        "artist": "Helena Vondrackova",
        "release_year": 1967,
        "country": "Czechoslovakia"
    },
    {
        "title": "Horis to moro mou",
        "source": "0qxNex5RfUe19yvnfUqMU0",
        "artist": "Anna Vissi",
        "release_year": 2000,
        "country": "Greece"
    },
    {
        "title": "Whenever, Wherever",
        "source": "2lnzGkdtDj5mtlcOW2yRtG",
        "artist": "Shakira",
        "release_year": 2001,
        "country": "Colombia"
    },
    {
        "title": "Talk Dirty",
        "source": "2zFzwIQ7QdOnSWMKUQZRf7",
        "artist": "Jason Derulo",
        "release_year": 2013,
        "country": "Haiti"
    },
    {
        "title": "Bylas Dla Mnie Wszystkim",
        "source": "1gdq80dLo5STca9yMgFO6a",
        "artist": "Poparzeni kawa trzy",
        "release_year": 2013,
        "country": "Poland"
    },
    {
        "title": "Mama mea e florăreasă",
        "source": "6X1XoVc0v4oSkvR4ZfsgrB",
        "artist": "Damian & Brothers",
        "release_year": 2016,
        "country": "Romania"
    },
    {
        "title": "Physical",
        "source": "3AzjcOeAmA57TIOr9zF1ZW",
        "artist": "Dua Lipa",
        "release_year": 2020,
        "country": "Albania"
    }
]